pandas_pretty_display/__init__.py
pandas_pretty_display/styler.py
pandas_pretty_display-0.3.5.dist-info/LICENSE
pandas_pretty_display-0.3.5.dist-info/METADATA
pandas_pretty_display-0.3.5.dist-info/WHEEL
pandas_pretty_display-0.3.5.dist-info/top_level.txt
pandas_pretty_display-0.3.5.dist-info/RECORD
