Metadata-Version: 2.1
Name: pandas-pretty-display
Version: 0.3.5
Summary: A package to make pandas DataFrames display beautifully in Jupyter notebooks
Home-page: https://github.com/bala-srm/pandas-pretty-display-.git
Author: Balaji
Author-email: bala@python4u.in
Classifier: Development Status :: 3 - Alpha
Classifier: Intended Audience :: Developers
Classifier: License :: OSI Approved :: MIT License
Classifier: Operating System :: OS Independent
Classifier: Programming Language :: Python :: 3
Classifier: Programming Language :: Python :: 3.6
Classifier: Programming Language :: Python :: 3.7
Classifier: Programming Language :: Python :: 3.8
Classifier: Programming Language :: Python :: 3.9
Requires-Python: >=3.6
License-File: LICENSE
Requires-Dist: ipython>=7.0.0
Requires-Dist: pandas>=1.0.0
